protloc_mex_X/__init__.py
protloc_mex_X/ESM2_fr.py
protloc_mex_X/examples/test1.txt
protloc_mex_X/feature_corrlation.py
protloc_mex_x-0.0.27.dist-info/LICENSE.txt
protloc_mex_x-0.0.27.dist-info/METADATA
protloc_mex_x-0.0.27.dist-info/WHEEL
protloc_mex_x-0.0.27.dist-info/RECORD
