Metadata-Version: 2.3
Name: protloc_mex_X
Version: 0.0.27
Summary: ...
License: MIT
Author: Ze Yu Luo
Author-email: 1024226968@qq.com
Requires-Python: >=3.9
Classifier: Development Status :: 3 - Alpha
Classifier: License :: OSI Approved :: MIT License
Classifier: Operating System :: OS Independent
Classifier: Programming Language :: Python :: 3
Classifier: Programming Language :: Python :: 3.9
Classifier: Programming Language :: Python :: 3.10
Classifier: Programming Language :: Python :: 3.11
Classifier: Programming Language :: Python :: 3.12
Classifier: Programming Language :: Python :: 3.13
Requires-Dist: matplotlib (==3.5.1)
Requires-Dist: numpy (==1.20.3)
Requires-Dist: pandas (==1.4.1)
Requires-Dist: seaborn (==0.11.2)
Project-URL: Documentation, https://github.com/yujuan-zhang/ProtLoc-mexl/issues
Project-URL: Homepage, https://github.com/yujuan-zhang/ProtLoc-mexl
Project-URL: Repository, https://github.com/yujuan-zhang/ProtLoc-mexl
